mcp_clipboard_server/__init__.py
mcp_clipboard_server/__main__.py
mcp_clipboard_server/_clipboard_utils.py
mcp_clipboard_server/_errors.py
mcp_clipboard_server/_logging_config.py
mcp_clipboard_server/_mcp_handler.py
mcp_clipboard_server/_protocol_types.py
mcp_clipboard_server/_tool_schemas.py
mcp_clipboard_server/_validators.py
mcp_clipboard_server/_version.py
mcp_clipboard_server/cli.py
mcp_clipboard_server/clipboard.py
mcp_clipboard_server/protocol.py
mcp_clipboard_server/server.py
mcp_clipboard_server/tools.py
mcp_clipboardify-1.0.0.dist-info/METADATA
mcp_clipboardify-1.0.0.dist-info/WHEEL
mcp_clipboardify-1.0.0.dist-info/entry_points.txt
mcp_clipboardify-1.0.0.dist-info/RECORD
