Metadata-Version: 2.3
Name: mcp-clipboardify
Version: 1.0.0
Summary: MCP server providing clipboard access tools for AI assistants and automation workflows
License: MIT
Keywords: mcp,clipboard,ai,automation,json-rpc,tools
Author: MCP Clipboard Server Contributors
Maintainer: MCP Clipboard Server Contributors
Requires-Python: >=3.11,<4.0
Classifier: Development Status :: 4 - Beta
Classifier: Intended Audience :: Developers
Classifier: License :: OSI Approved :: MIT License
Classifier: Operating System :: OS Independent
Classifier: Programming Language :: Python :: 3
Classifier: Programming Language :: Python :: 3.11
Classifier: Programming Language :: Python :: 3.12
Classifier: Programming Language :: Python :: 3.13
Classifier: Programming Language :: Python :: 3.10
Classifier: Programming Language :: Python :: 3.8
Classifier: Programming Language :: Python :: 3.9
Classifier: Topic :: Software Development :: Libraries :: Python Modules
Classifier: Topic :: System :: System Shells
Classifier: Topic :: Utilities
Requires-Dist: pyperclip (>=1.8.2,<2.0.0)
Project-URL: Bug Tracker, https://github.com/fluffypony/mcp-clipboardify/issues
Project-URL: Changelog, https://github.com/fluffypony/mcp-clipboardify/blob/main/CHANGELOG.md
Project-URL: Documentation, https://github.com/fluffypony/mcp-clipboardify/blob/main/README.md
Project-URL: Homepage, https://github.com/fluffypony/mcp-clipboardify
Project-URL: Repository, https://github.com/fluffypony/mcp-clipboardify
